{"paths":{},"types":[],"uuids":["00oofwDtdEXrC769oZhgA3","06Nz9snfRHsqYBrk7G4lsO","0fQMIchGNC34E4HbR+12cD","15PZAsKfZHvoAnd7uumsLA","1bxLsUahJHv7H5lTri1zwN","1cptkdpR9LwqBSpT8lzwv6","1fJXwpXK1D5bZQ4MaW0cJr","22qWx3joJFe5brQbvzgRKJ","29cAIOSBNMq56dmfiDLbcO","2bpGbnujlHopBRiCnpZHJe","30oc12trpMXIukoh94Lq6w","41HmdxMKlHsKwYBeM1KBo5","42Jp/VOlFAqLOL4sCCNCbw","44MS52h+NBgITyM7TAb2Yw","46pTCMyk1FgqUdLA4eRWKJ","48Hm8ucKNEFqr/qNtR9pHj","48Nr+5VFpPuYMIYdBBwwxl","48uFXJuEBHaItdoExSpxfE","4843qSqUpDNZdOErs79d4K","4aHPkFJklG2IK/WeAFkW9M","51KvgBkFJGJrEZFVHUVoTy","57nIAm9H5K7Yxu7dBR0KDJ","5a1JTrfHVDu7ByD++zfSfO","5edZYEU95N+5P7559J6Fk1","609v1Aq6dIzbwEqCy5gFKo","61cyPdEfRN047sDK9rO0W5","672uoYbuhPUrAZBjZWXJ/p","6b3QZvKOhPFo8xrQ6DL+aF","6cH94321NKK77h1RETgYH/","6cSKNE9JFAbpTTqN+oDjBB","6efb5RcidI+ZSYUYo5Q2s2","71VhFCTINJM6/Ky3oX9nBT","75DYv/OOlNfLDXYQFwHlTQ","78N1XSWm5CqI3VREfWfkhY","80whfynNdANZouUl3PmxsM","85/s4vSO1M3asbwVPNEr7a","86ykZ1uG5Pn4LUYdSQRuMX","8eAExRdXZHF7Jvi7mf0Oye","91pX4yq2dDAJy6ft3t5E5y","96/4aiSvVCKqx0DdVlaI9D","99D6C0W+5FgbKE1ZbTKjBU","9bsJ9oCYtP4YIlVKpR9o0x","9c78Xu6u1KEoJrR78Lwb0U","a1S+6x505PN7lk1sVLm5WQ","a6HqjVqpNH8oz3sk/JD5Il","a6R1g/MKZL5rcsVLRvE2Nq","aaG5gxA7pFQ71DRrdSbMnW","aalzVEgWZDwr1qSmQZGzuk","b1jiwDsupN1JI0F7RtmOsZ","b4P/PCArtIdIH38t6mlw8Y","b5vY27KddHJ4N/wQKXAJCJ","b6VX1FpJBKJbpwdnySmdav","b7hKCUocFFzJZjfFhown+j","bdPxBxnf9L3aezA1m1x8en","c90TZvfTRFjqJBIYRaa+0c","cdbJCNN4tB1raOcraWyLnN","d1RQzarAlLo7R1pkfNsE2S","d3AB++SFJD/b7Czii2Ndc5","d608qFRoFHwbXd0Dap056i","d7bKZ4qUxMwIFUdnpy8Bse","d8HsitJHxOYqo801xBk8ev","dd0XclFY9CJpe7hOYjEn5h","e1lA4sRzROur5YqeWXSSer","e3Y1n9TN5PRonu+uTotCPf","e4h5xsz/9Ag7oHHp5iUEhU","e404vkZV1Lf4qlDe3jMOwb","e8Ueib+qJEhL6mXAHdnwbi","f3SihRLeZJ7pdAi1NouS9z","f5DSVzIplNarcrPZvPeUdJ","fbc+ZOfrVEc6PT4y2wGclp","fb8wMXDcJOpIjhJqiafTMh","fc5aeyTadCKaZdPGUR7dry","feO/+jjANE5r+0m4okgs7R","01Ztn/4N9GCr8XhE9tX5zu","01dk89V/ZDyL+VWzK8POiW","02LTRpzXRPEIkS95bgPvIG","02delMVqdBD70a/HSD99FK","04R3EVKcJILpwUBmkhigip","04qFwB7C5KAocTa42vsf1W","08huNvrw9LYb0rBFCqKXvu","0885eF6z1HPYDrNTguyAbJ","0cZWkbcEdKC6tXxXblRqMs","0dd0rL+5BMmqMDima1zy8L","11Qx0iUEdKG4oD25j84gXk","14iWyZPI5NCqZoZz5Mklm8","15+Mv45hZP1aJLxauaGK46","16xRt0HxBDApq1tDCxTIAu","17QvBZm/xFEpUIcXJzI01P","1bU9ky/GxK7akx0QpLht9q","1evKcOPjpB+poSTj7JE/08","21kert2eVNT7G1X5nC0piZ","21lRE5vf1P3JwNaN5FhR4o","21125PP8VIL7mDabzrQmNW","24X0UdM+tK7JBFG/b2vLH0","25znKOzLRIAbihnz8GjufR","27u0DAP2pEXL+P3HkbvMf0","29FYIk+N1GYaeWH/q1NxQO","30JWcIDVJDt4PpcPVallpE","33kLQVQBBE1pZY1E7Sk8ej","3dri76ZKxEBJWVepX+aR5k","3eLPF4gq9IRpF8Wsc3gnz0","40Rx/gxJ9Gm4DQRIxiuCwe","45RvyxVApIA4M9hS96xQIF","48RPXbW+dD4ps1A2GfMQVK","4d02huugtHW40nDeFR411j","4f8brHyM1NGaKKZwcTBkhZ","51Rnjxvd5Gkqd3JMm/IE2o","55pF8PanJHJ5ZlTFDp53nW","5buH+Ht/NPx4U9BAoLg6go","5cO7kybDxGj4ipyMYdRYZB","5cRLDHsS1I7Y+uuP7CRpRg","5eNe+ZVX5JX56MuMkQOjwt","5fZ38qqmJAfpsRm8ZiVdx0","5f5dyqtRNNxaFmVzYns6FZ","63U4tqE6xDBojqsOiTLGYM","64hBako5RDpK4ZtdjJ57br","68NMI5c2tNNblIlOhhAQaP","68doFgnoNCDaQosI2UlHVP","69O6uSptZP17u0rsiIixCM","6aNaBVs7BOAYKWuApzr++y","6fDVG326JOWI5RcEUZc/o+","6f91tNo69KN6fwwFwUPmwV","71vvyyb+tIfI5vlsIJz5aH","741ecjH8hN64CPt5avdQXB","759XwOEtFGloTBNwyBPfYI","75/DO2dJ9Dq4AMIFi6O+/+","78n3caY89A/Iln7wIjVJyu","7e9JhuNuNMqrUfCjz/nybI","82qEtH75RO26sRexPM8GdK","8ad9N8wMRDI4IXLL1WN9/A","8bcKKynDRPRKT9Tz/9XxPT","8byVhITjlNpbkhrSrH7dAZ","904gNqcAxFBpXq5OBEzvf9","94Nczx3iFH/Llol/QUPFuV","94qbGed0JM5ajePw39+O6X","99X6Jbrl1Glo80vXIGG74l","9bvaMerUlDyary99mJa6xp","9d3lQVrClCOa4aNzrTYqP+","9eEoKvBVdNVJLTbdP22eyl","a2MjXRFdtLlYQ5ouAFv/+R","a3rdJjtLpPFLZkayfP9CFz","a4nwEpAh1N2Zqded6XP1Bh","a6ECL4HA9C86QEKuKIvdIk","a7XcK8ZYZMsYGTNLYSY2vd","a8cbDYqEpBtLrwEHTZyyDC","aav7Gs1AVOKpJmlP0GnELh","adN82/LKZGU6680BZrtYdx","b36u2rjixFO5NoXRkYfWCD","b4Bv3xo1VBRIN8DoZUHlke","b7O9oXxU9CoJnFkjDes7ir","b8UpJjD6FD67HONWTBAdIb","b8qKRhbW9BD64r1/UE3Oe9","bbYNULvZFCvph8n9fSav7z","beDFQMrFVOdKKsLHXzwxwK","bfNy//VBJPYo3kDt3aZucN","bf3XAdnsVN1orh96C0vQ+4","c02Jlq3WdML7ChVKPQ94LK","c3eOBfWtVIaaabOI9z7+ia","c5X2CaNcFGGJ+r4vZ0dOex","c6QJGuDvxPS7XeKNsvA5XD","c6+e1QMtBN7ZjeIA5T8RVU","c7766Pw/NHeJJAeOoEuFMG","c8AkP97WJH663Rw+/sNRPm","c9o1BQ52pDQ6dEl6FqyD6R","ccZY1quhJJuYUDqu+o4acp","ceOucd54xCq5ietWp/HNlq","d0E7/7Jz9HKIFhoaN5aChI","d2hILrHARIOITs0AYI5FtH","d5OS6yZNVJr5lULqRbZHos","e3Le6LCmxARJPPOd642Wug","e9WLrZq/9Fe6vEGSffKuwq","e97GVMl6JHh5Ml5qEDdSGa","eaXdLCCq5C64F93k7rMeHZ","ecJlykJ7NJMajDPHdUjAYL","ecpdLyjvZBwrvm+cedCcQy","efdpZ1DzZCxLEEEqA1wfIC","f0BIwQ8D5Ml7nTNQbh1YlS","f0cI0XPehOfLyF8aQi4PO4","f27gUcNLlEebZ9NXd8zjVG","f3keneeKtC2qlkCVylkFmc","f5btGcNnRDyL2w6t25LMC/","f6w6npiPJND7b19IjEYjgQ","farZMODQtCiIf5IljvM3UY","fc5U9BSVBNopQTc0n5f9Pu"],"scenes":{"db://assets/launch/launch.fire":63,"db://assets/scene/gameScene.fire":48,"db://assets/scene/Invite.fire":42,"db://assets/scene/main.fire":4,"db://assets/scene/Mine.fire":34,"db://assets/scene/Store.fire":16},"redirect":[74,0,76,1,79,0,85,0,88,0,89,0,97,0,108,0,110,0,111,0,112,0,126,0,133,0,137,0,145,0,152,0,162,0,164,0,174,1,175,0,180,0],"deps":["resources","internal"],"packs":{"012066da4":[75,91,95,104,120,123,125,34,144,166,178,181,182],"0239644af":[20,117,156,161],"03bbceb5b":[73,77,1,80,81,83,84,86,87,92,94,99,106,115,119,121,122,128,129,130,135,140,142,143,146,48,149,150,151,154,159,168,170,173,177,179,183],"04a2fdbac":[101,163],"06d12686d":[78,96,102,109,113,116,136,42,165,171,176],"07a47b8b0":[100,103,138,158],"07fc3adac":[114,127,141],"09b6096f4":[82,4,98,105,107,118,124,132,147,148,153,155,157,160,167,169],"0c77ebce6":[131,63],"0d09820d1":[90,139,62],"0eb08e326":[0,2,3,5,6,7,8,9,10,11,12,13,14,15,17,18,19,21,22,23,24,25,26,27,28,29,30,31,32,33,35,36,37,38,39,40,41,43,44,45,46,47,49,50,51,52,53,54,55,56,57,58,59,60,61,64,65,66,67,68,69,70,71,72]},"name":"main","importBase":"import","nativeBase":"native","debug":false,"isZip":false,"encrypted":false,"versions":{"import":["012066da4","416b5","0239644af","11a75","03bbceb5b","2bbfb","04a2fdbac","dbc73","06d12686d","e5709","07a47b8b0","145f8","07fc3adac","d42b7","09b6096f4","dec1d","0c77ebce6","501a3","0d09820d1","fe70b","0eb08e326","998d9",93,"28da5",16,"7fd23",134,"a6998",172,"957aa"],"native":[0,"1096e",1,"4a925",2,"b8e66",3,"64214",5,"98abe",6,"8e560",7,"5d1c9",8,"398a2",9,"885a7",10,"6c24b",11,"42b44",12,"e2674",13,"89c46",14,"bee18",15,"6b932",17,"abc78",18,"259c4",19,"a3fe7",20,"de8d0",21,"d0869",22,"6378f",23,"5c6a0",24,"a7f42",25,"6d707",26,"901d9",27,"4b03d",28,"c17ce",29,"a398e",30,"e2d05",31,"c06a9",32,"a367f",33,"27373",35,"c29e6",36,"c209e",37,"8e326",38,"15eba",39,"6cbf8",40,"9ab02",41,"41129",43,"aa9f8",44,"4539f",45,"ca430",46,"2c6bf",47,"4b91a",49,"83fcc",50,"9f7b0",51,"b13a1",52,"4c611",53,"ac7c5",54,"00fd1",55,"517c3",56,"e95c1",57,"1a7fe",58,"d55c2",59,"72bbf",60,"cdbc9",61,"ff5fc",62,"e5a3d",64,"bdc90",65,"e4acc",66,"90cf4",67,"3bb6e",68,"d3cc0",69,"91ed1",70,"9aa60",71,"a1189",72,"9a07b"]}}